{
  "offerId": "dharmapurimay25",
  "title": "Dibrugarh City Offers | SBI Card",
  "description": "Pay Online",
  "validity": "",
  "tnc": "Install\n\nManage your account on the go with the SBI Card Mobile App\n\nNew User?\nRegister Now\n \nLogin\nMenu\nQuick Links\nSearch\nApply Now\nGet In Touch\n\n     \n\n◀Back to Offers list\nOffer Details\nTerms and Conditions\nEligible Cards\n\nAll SBI Credit Cards\n\nSummary\n\nS.No.\n\n\t\n\nStore Name\n\n\t\n\nCategory\n\n\t\n\nOffer\n\n\t\n\nAddress\n\n\t\n\nCity\n\n\t\n\nState\n\n\t\n\nPin Code\n\n\t\n\nOffer End date\n\n\n\n\n1\n\n\t\n\nAbhishek Mens Wear\n\n\t\n\nApparel\n\n\t\n\n15% off on Total Bill\n\n\t\n\nShop No. 105A, Chinnaswamy Naidu Street, Dharmapuri, Tamil Nadu\n\n\t\n\nDharmapuri\n\n\t\n\nTamil Nadu\n\n\t\n\n636701\n\n\t\n\n31-Jan-26\n\n\n\n\n2\n\n\t\n\nAmro\n\n\t\n\nApparel\n\n\t\n\n50% off on Total Bill\n\n\t\n\nShop No. 15A, Nachiappa Vassu Gounder Street, Dharmapuri, Tamil Nadu\n\n\t\n\nDharmapuri\n\n\t\n\nTamil Nadu\n\n\t\n\n636701\n\n\t\n\n31-Jan-26\n\n\n\n\n3\n\n\t\n\nArun Mobiles\n\n\t\n\nMobile\n\n\t\n\n15% off on Mobile Phones on MRP Except One Plus and Apple Products\n\n\t\n\nShop No. 21C, Pennagaram Main Road, Near By Indian Bank, Dharmapuri Bazaar, Dharmapuri, Tamil Nadu\n\n\t\n\nDharmapuri\n\n\t\n\nTamil Nadu\n\n\t\n\n636701\n\n\t\n\n31-Jan-26\n\n\n\n\n4\n\n\t\n\nBright Furnitures\n\n\t\n\nFurniture\n\n\t\n\n25% off on Total Bill\n\n\t\n\nShop No. 18 A, Siddha Veerappa Chetty Street, Opposite Senthi Kumar Department, Dharmapuri - ()\n\n\t\n\nDharmapuri\n\n\t\n\nTamil Nadu\n\n\t\n\n636701\n\n\t\n\n31-Jan-26\n\n\n\n\n5\n\n\t\n\nBright Furnitures Rexine & Foams\n\n\t\n\nFurniture\n\n\t\n\n25% off on Total Bill\n\n\t\n\nShop No. 14, Santai Road, Opposite Gokul Manabam, Dharmapuri, Tamil Nadu\n\n\t\n\nDharmapuri\n\n\t\n\nTamil Nadu\n\n\t\n\n636701\n\n\t\n\n31-Jan-26\n\n\n\n\n6\n\n\t\n\nDhanlaxmi Silks & Readymades\n\n\t\n\nApparel\n\n\t\n\n15% off on Total Bill\n\n\t\n\nShop No. 13/14, Chinnaswamy Naidu Street, Dharmapuri, Tamil Nadu\n\n\t\n\nDharmapuri\n\n\t\n\nTamil Nadu\n\n\t\n\n636701\n\n\t\n\n31-Jan-26\n\n\n\n\n7\n\n\t\n\nElakiya Enterprises\n\n\t\n\nMobile\n\n\t\n\n15% off on Mobile Phones on MRP Except One Plus and Apple Products\n\n\t\n\nShop No. 146, Pennagaram Main Road, Dharmapuri, Tamil Nadu\n\n\t\n\nDharmapuri\n\n\t\n\nTamil Nadu\n\n\t\n\n636701\n\n\t\n\n31-Jan-26\n\n\n\n\n8\n\n\t\n\nGoutham Electronicx\n\n\t\n\nElectronics\n\n\t\n\n20% off on Electronic Products on MRP\n\n\t\n\nShop No. 9 A, Arumuga Achari Street, Arumuga Achari Street, Dharmapuri, Tamil Nadu\n\n\t\n\nDharmapuri\n\n\t\n\nTamil Nadu\n\n\t\n\n636701\n\n\t\n\n31-Jan-26\n\n\n\n\n9\n\n\t\n\nMr.Thadikkaran Fashion Farmers\n\n\t\n\nApparel\n\n\t\n\n15% off on Total Bill\n\n\t\n\nShop No. 7, Sivasakthi Complex, Near Om Sakti Hospital, Dharmapuri, Tamil Nadu\n\n\t\n\nDharmapuri\n\n\t\n\nTamil Nadu\n\n\t\n\n636701\n\n\t\n\n31-Jan-26\n\n\n\n\n10\n\n\t\n\nRoyal Furniture Point\n\n\t\n\nFurniture\n\n\t\n\n20% off on Total Bill\n\n\t\n\nShop No. 136, Nethaji Bypass, Agarwar Hospital Basement, Dharmapuri, Tamil Nadu\n\n\t\n\nDharmapuri\n\n\t\n\nTamil Nadu\n\n\t\n\n636701\n\n\t\n\n31-Jan-26\n\n\n\n\n11\n\n\t\n\nShankar Home Appliances\n\n\t\n\nHome Appliances\n\n\t\n\n25% off on Electronic Products on MRP\n\n\t\n\nShop No. 39/19, Arumuga Achari Street, Dharmapuri, Tamil Nadu\n\n\t\n\nDharmapuri\n\n\t\n\nTamil Nadu\n\n\t\n\n636701\n\n\t\n\n31-Jan-26\n\n\n\n\n12\n\n\t\n\nSubhalaxmi silks & Readymades\n\n\t\n\nApparel\n\n\t\n\n15% off on Total Bill\n\n\t\n\nShop No. 61/10, Chinnaswamy Naidu Street, Dharmapuri, Tamil Nadu\n\n\t\n\nDharmapuri\n\n\t\n\nTamil Nadu\n\n\t\n\n636701\n\n\t\n\n31-Jan-26\n\n\n\n\n13\n\n\t\n\nUp2Date Mens Wear\n\n\t\n\nApparel\n\n\t\n\n20% off on Total Bill\n\n\t\n\nShop No. 2A, Siddhaveerappa Chetty Street, Chinnasamy Naidu Street, Dharmapuri, Tamil Nadu\n\n\t\n\nDharmapuri\n\n\t\n\nTamil Nadu\n\n\t\n\n636702\n\n\t\n\n31-Jan-26\n\n\n\n\n14\n\n\t\n\nV2 Outfitters\n\n\t\n\nApparel\n\n\t\n\n20% off on Total Bill\n\n\t\n\nShop No. 33/3E, S.R Complex, Siddha Veerppa Chetty Street, Dharmapuri, Tamil Nadu\n\n\t\n\nDharmapuri\n\n\t\n\nTamil Nadu\n\n\t\n\n636701\n\n\t\n\n31-Jan-26\n\n\n\n\n15\n\n\t\n\nYuva Mens Wear\n\n\t\n\nApparel\n\n\t\n\n20% off on Total Bill\n\n\t\n\nShop No. 28F, Siddha Veerppa Chetty Street, Dharmapuri, Tamil Nadu\n\n\t\n\nDharmapuri\n\n\t\n\nTamil Nadu\n\n\t\n\n636701\n\n\t\n\n31-Jan-26\n\nSteps to avail this offer\n\nAvail these offers by visiting the respective Stores and by using your SBI Credit Card.\n\nFor more details, please refer to the TnC document\n\nDownload Mobile App\nMobile Icon\nApple's App Store\n\t\nGoogle's Play Store\n\t\nWindow's Store\nBack to top\nPersonal\nCorporate\nWho We Are\nGet In Touch\nBlog\nHelp\nCredit Cards\nBenefits\nPay\nOffers\nRewards\nApply\n© 2025 Do Not Disturb Most Important Terms & Conditions Offer Terms & Conditions Security Forms Central Sitemap Disclaimer Fair Practice Code Credit Bureau FAQs Privacy Policy/Notice PoSH Policy Order of Payment Settlement Cardholder Agreement Usage Agreement Customer Grievance Redressal Policy Customer Notices Tokenisation Procurement News ODR Portal Link & Circular for Shareholders Policy for the issuance and conduct of credit cards\n\n\n\n\"SBI Cards and Payment Services Limited” was formerly known as “SBI Cards and Payment Services Private Limited\"\n\n\n\n\nSite best viewed in browsers I.E 11+, Mozilla 3.5+, Chrome 3.0+, Safari 5.0+ on all desktops, laptops, and Android & iOS mobile/tablet devices\n\nx\n\nYou are being re-directed to a third party site. Please acknowledge the disclaimer before proceeding further.\n\nYou are about to access a site, the accuracy or completeness of the materials or the reliability of any advice, opinion, statement or other information displayed or distributed through it, is not warranted by SBICPSL and shall be solely be construed to be set forth by the third party.\n\nYou will access this site solely for the payment of your bills and you acknowledge that any reliance on any opinion, advice, statement, memorandum, or information available on the site shall be at your sole risk and consequences.\n\nSBICPSL and its affiliates, subsidiaries, employees, officers, directors and agents, expressly disclaim any liability for any deficiency in the services of the service provider whose site you are about to access. Neither SBICPSL nor any of its affiliates nor their directors, officers and employees will be liable to or have any responsibility of any kind for any loss that you incur in the event of any deficiency in the services of the service provider, failure or disruption of the site of the service provider, or resulting from the act or omission of any other party involved in making this site or the data contained therein available to you, or from any other cause relating to your access to, inability to access, or use of the site or these materials in accordance thereto SBICSPL and all its related parties described hereinabove stand indemnified from all proceedings or matters arising thereto.\n\nOKCancel",
  "eligibleCards": [
    "SBI and Payment Services Limited” was formerly known as “SBI Cards and Payment Services Private Limited\" Site best viewed in browsers I.E 11+",
    "SBI Mozilla 3.5+",
    "SBI Chrome 3.0+",
    "SBI Safari 5.0+ on all desktops",
    "SBI laptops",
    "SBI and Android & iOS mobile/tablet devices x You are being re-directed to a third party site. Please acknowledge the disclaimer before proceeding further. You are about to access a site",
    "SBI the accuracy or completeness of the materials or the reliability of any advice",
    "SBI opinion",
    "SBI statement or other information displayed or distributed through it",
    "SBI is not warranted by SBICPSL and shall be solely be construed to be set forth by the third party. You will access this site solely for the payment of your bills and you acknowledge that any reliance on any opinion",
    "SBI advice",
    "SBI statement",
    "SBI memorandum",
    "SBI or information available on the site shall be at your sole risk and consequences. SBICPSL and its affiliates",
    "SBI subsidiaries",
    "SBI employees",
    "SBI officers",
    "SBI directors and agents",
    "SBI expressly disclaim any liability for any deficiency in the services of the service provider whose site you are about to access. Neither SBICPSL nor any of its affiliates nor their directors",
    "SBI officers and employees will be liable to or have any responsibility of any kind for any loss that you incur in the event of any deficiency in the services of the service provider",
    "SBI failure or disruption of the site of the service provider",
    "SBI or resulting from the act or omission of any other party involved in making this site or the data contained therein available to you",
    "SBI or from any other cause relating to your access to",
    "SBI inability to access",
    "SBI or use of the site or these materials in accordance thereto SBICSPL and all its related parties described hereinabove stand indemnified from all proceedings or matters arising thereto. OKCancel"
  ],
  "excludedCards": [
    "SBI Card ELITE",
    "SBI Card PRIME",
    "SBI SimplyCLICK Card",
    "SBI SimplySAVE Card",
    "SBI Card Unnati",
    "SBI Card PRIME Advantage",
    "SBI Card ELITE Advantage",
    "SBI Card PULSE",
    "SBI Card AURUM",
    "SBI IRCTC Card",
    "SBI IRCTC Premier Card",
    "SBI BPCL Card",
    "SBI BPCL Octane Card",
    "SBI Air India Card",
    "SBI Air India Signature Card",
    "SBI Club Vistara Card",
    "SBI Club Vistara PRIME Card",
    "SBI Apollo SBI Card",
    "SBI Shaurya Card",
    "SBI Shaurya Select Card",
    "SBI Ola Money Card",
    "SBI Paytm Card",
    "SBI Paytm SELECT Card",
    "SBI FBB Card",
    "SBI Yatra Card",
    "SBI Mumbai Metro Card",
    "SBI Delhi Metro Card",
    "SBI Chennai Metro Card",
    "SBI Etihad Guest Card",
    "SBI Etihad Guest Premier Card",
    "SBI Tata Card",
    "SBI Tata Platinum Card",
    "SBI SimplyCLICK Advantage Card",
    "SBI SimplySAVE Advantage Card",
    "SBI Card PRIME Advantage",
    "SBI Card ELITE Advantage"
  ]
}